{
   "runs" : [
      {
         "OS" : "linux",
         "abstract" : "Compare two dates with approximate parsing support",
         "dir" : "/home/runner/work/Date-Cmp/Date-Cmp",
         "finish" : 1784465274.02808,
         "name" : "Date-Cmp",
         "perl" : "5.40.4",
         "run" : "-e",
         "start" : 1784465262.49109,
         "version" : "0.06"
      },
      {
         "OS" : "linux",
         "abstract" : "Compare two dates with approximate parsing support",
         "dir" : "/home/runner/work/Date-Cmp/Date-Cmp",
         "finish" : 1784465262.63847,
         "name" : "Date-Cmp",
         "perl" : "5.40.4",
         "run" : "-e",
         "start" : 1784465262.63837,
         "version" : "0.06"
      },
      {
         "OS" : "linux",
         "abstract" : "Compare two dates with approximate parsing support",
         "dir" : "/home/runner/work/Date-Cmp/Date-Cmp",
         "finish" : 1784465263.50227,
         "name" : "Date-Cmp",
         "perl" : "5.40.4",
         "run" : "t/30-basics.t",
         "start" : 1784465263.31677,
         "version" : "0.06"
      },
      {
         "OS" : "linux",
         "abstract" : "Compare two dates with approximate parsing support",
         "dir" : "/home/runner/work/Date-Cmp/Date-Cmp",
         "finish" : 1784465264.56241,
         "name" : "Date-Cmp",
         "perl" : "5.40.4",
         "run" : "t/cmp.t",
         "start" : 1784465264.3098,
         "version" : "0.06"
      },
      {
         "OS" : "linux",
         "abstract" : "Compare two dates with approximate parsing support",
         "dir" : "/home/runner/work/Date-Cmp/Date-Cmp",
         "finish" : 1784465265.57191,
         "name" : "Date-Cmp",
         "perl" : "5.40.4",
         "run" : "t/datecmp.t",
         "start" : 1784465265.36388,
         "version" : "0.06"
      },
      {
         "OS" : "linux",
         "abstract" : "Compare two dates with approximate parsing support",
         "dir" : "/home/runner/work/Date-Cmp/Date-Cmp",
         "finish" : 1784465266.51911,
         "name" : "Date-Cmp",
         "perl" : "5.40.4",
         "run" : "t/edge_cases.t",
         "start" : 1784465266.39446,
         "version" : "0.06"
      },
      {
         "OS" : "linux",
         "abstract" : "Compare two dates with approximate parsing support",
         "dir" : "/home/runner/work/Date-Cmp/Date-Cmp",
         "finish" : 1784465266.9671,
         "name" : "Date-Cmp",
         "perl" : "5.40.4",
         "run" : "t/eof.t",
         "start" : 1784465266.96681,
         "version" : "0.06"
      },
      {
         "OS" : "linux",
         "abstract" : "Compare two dates with approximate parsing support",
         "dir" : "/home/runner/work/Date-Cmp/Date-Cmp",
         "finish" : 1784465267.20616,
         "name" : "Date-Cmp",
         "perl" : "5.40.4",
         "run" : "t/eol.t",
         "start" : 1784465267.20582,
         "version" : "0.06"
      },
      {
         "OS" : "linux",
         "abstract" : "Compare two dates with approximate parsing support",
         "dir" : "/home/runner/work/Date-Cmp/Date-Cmp",
         "finish" : 1784465267.91596,
         "name" : "Date-Cmp",
         "perl" : "5.40.4",
         "run" : "t/extended_tests.t",
         "start" : 1784465267.89065,
         "version" : "0.06"
      },
      {
         "OS" : "linux",
         "abstract" : "Compare two dates with approximate parsing support",
         "dir" : "/home/runner/work/Date-Cmp/Date-Cmp",
         "finish" : 1784465269.09319,
         "name" : "Date-Cmp",
         "perl" : "5.40.4",
         "run" : "t/function.t",
         "start" : 1784465268.77587,
         "version" : "0.06"
      },
      {
         "OS" : "linux",
         "abstract" : "Compare two dates with approximate parsing support",
         "dir" : "/home/runner/work/Date-Cmp/Date-Cmp",
         "finish" : 1784465270.63556,
         "name" : "Date-Cmp",
         "perl" : "5.40.4",
         "run" : "t/integration.t",
         "start" : 1784465269.97845,
         "version" : "0.06"
      },
      {
         "OS" : "linux",
         "abstract" : "Compare two dates with approximate parsing support",
         "dir" : "/home/runner/work/Date-Cmp/Date-Cmp",
         "finish" : 1784465270.55292,
         "name" : "Date-Cmp",
         "perl" : "5.40.4",
         "run" : "/tmp/date_cmp_load_16814.pl",
         "start" : 1784465270.53426,
         "version" : "0.06"
      },
      {
         "OS" : "linux",
         "abstract" : "Compare two dates with approximate parsing support",
         "dir" : "/home/runner/work/Date-Cmp/Date-Cmp",
         "finish" : 1784465271.7184,
         "name" : "Date-Cmp",
         "perl" : "5.40.4",
         "run" : "t/locales.t",
         "start" : 1784465271.51287,
         "version" : "0.06"
      },
      {
         "OS" : "linux",
         "abstract" : "Compare two dates with approximate parsing support",
         "dir" : "/home/runner/work/Date-Cmp/Date-Cmp",
         "finish" : 1784465272.10408,
         "name" : "Date-Cmp",
         "perl" : "5.40.4",
         "run" : "t/pod-cm.t",
         "start" : 1784465272.10381,
         "version" : "0.06"
      },
      {
         "OS" : "linux",
         "abstract" : "Compare two dates with approximate parsing support",
         "dir" : "/home/runner/work/Date-Cmp/Date-Cmp",
         "finish" : 1784465272.34169,
         "name" : "Date-Cmp",
         "perl" : "5.40.4",
         "run" : "t/pod-snippets.t",
         "start" : 1784465272.34146,
         "version" : "0.06"
      },
      {
         "OS" : "linux",
         "abstract" : "Compare two dates with approximate parsing support",
         "dir" : "/home/runner/work/Date-Cmp/Date-Cmp",
         "finish" : 1784465272.57722,
         "name" : "Date-Cmp",
         "perl" : "5.40.4",
         "run" : "t/pod-synopsis.t",
         "start" : 1784465272.57693,
         "version" : "0.06"
      },
      {
         "OS" : "linux",
         "abstract" : "Compare two dates with approximate parsing support",
         "dir" : "/home/runner/work/Date-Cmp/Date-Cmp",
         "finish" : 1784465272.81277,
         "name" : "Date-Cmp",
         "perl" : "5.40.4",
         "run" : "t/pod.t",
         "start" : 1784465272.81253,
         "version" : "0.06"
      },
      {
         "OS" : "linux",
         "abstract" : "Compare two dates with approximate parsing support",
         "dir" : "/home/runner/work/Date-Cmp/Date-Cmp",
         "finish" : 1784465273.80477,
         "name" : "Date-Cmp",
         "perl" : "5.40.4",
         "run" : "t/unit.t",
         "start" : 1784465273.49305,
         "version" : "0.06"
      }
   ],
   "summary" : {
      "/tmp/date_cmp_load_16814.pl" : {},
      "Total" : {
         "branch" : {
            "covered" : 164,
            "error" : 20,
            "percentage" : 89.1304347826087,
            "total" : 184,
            "uncoverable" : 0
         },
         "condition" : {
            "covered" : 98,
            "error" : 16,
            "percentage" : 85.9649122807018,
            "total" : 114,
            "uncoverable" : 0
         },
         "statement" : {
            "covered" : 202,
            "error" : 1,
            "percentage" : 99.5073891625616,
            "total" : 203
         },
         "subroutine" : {
            "covered" : 12,
            "percentage" : 100,
            "total" : 12
         },
         "total" : {
            "covered" : 476,
            "error" : 37,
            "percentage" : 92.7875243664717,
            "total" : 513,
            "uncoverable" : 0
         }
      },
      "blib/lib/Date/Cmp.pm" : {
         "branch" : {
            "covered" : 164,
            "error" : 20,
            "percentage" : 89.1304347826087,
            "total" : 184,
            "uncoverable" : 0
         },
         "condition" : {
            "covered" : 98,
            "error" : 16,
            "percentage" : 85.9649122807018,
            "total" : 114,
            "uncoverable" : 0
         },
         "statement" : {
            "covered" : 202,
            "error" : 1,
            "percentage" : 99.5073891625616,
            "total" : 203
         },
         "subroutine" : {
            "covered" : 12,
            "percentage" : 100,
            "total" : 12
         },
         "total" : {
            "covered" : 476,
            "error" : 37,
            "percentage" : 92.7875243664717,
            "total" : 513,
            "uncoverable" : 0
         }
      }
   }
}
